chainup_api_check/__init__.py
chainup_api_check/blockchain_checker/__init__.py
chainup_api_check/blockchain_checker/aptos.py
chainup_api_check/blockchain_checker/beacon.py
chainup_api_check/blockchain_checker/bitcoin.py
chainup_api_check/blockchain_checker/blockchain.py
chainup_api_check/blockchain_checker/bnb.py
chainup_api_check/blockchain_checker/cosmos.py
chainup_api_check/blockchain_checker/evm.py
chainup_api_check/blockchain_checker/near.py
chainup_api_check/blockchain_checker/polkadot.py
chainup_api_check/blockchain_checker/solana.py
chainup_api_check/blockchain_checker/ton.py
chainup_api_check/blockchain_checker/xrp.py
chainup_api_check/main.py
chainup_api_check/model/blockchain_status.py
chainup_api_check/util/send_jsonrpc.py
chainup_api_check-0.1.1.dist-info/METADATA
chainup_api_check-0.1.1.dist-info/WHEEL
chainup_api_check-0.1.1.dist-info/entry_points.txt
chainup_api_check-0.1.1.dist-info/RECORD
